MANIFEST.in
README.md
setup.py
eng_to_ipa/__init__.py
eng_to_ipa/rhymes.py
eng_to_ipa/stress.py
eng_to_ipa/syllables.py
eng_to_ipa/transcribe.py
eng_to_ipa/transcriber.py
eng_to_ipa.egg-info/PKG-INFO
eng_to_ipa.egg-info/SOURCES.txt
eng_to_ipa.egg-info/dependency_links.txt
eng_to_ipa.egg-info/top_level.txt
eng_to_ipa/resources/CMU_dict.db
eng_to_ipa/resources/CMU_dict.json
eng_to_ipa/resources/phones.json