Metadata-Version: 2.1
Name: eng-to-ipa
Version: 0.0.1
Summary: take English text and convert it to IPA
Home-page: UNKNOWN
Author: ['mphilli', 'Mitchellpkt', 'CanadianCommander', 'timvancann']
License: UNKNOWN
Platform: UNKNOWN
